thctools/__init__.py
thctools/index/__init__.py
thctools/index/kdj.py
thctools/index/ma.py
thctools/index/macd.py
thctools/index/rsi.py
thctools/test/__init__.py
thctools/test/test.py
thctools/util/__init__.py
thctools/util/base.py
thctools/util/common.py
util/__init__.py
util/base.py
util/common.py
thctools-1.0.3.dist-info/LICENSE
thctools-1.0.3.dist-info/METADATA
thctools-1.0.3.dist-info/WHEEL
thctools-1.0.3.dist-info/top_level.txt
thctools-1.0.3.dist-info/RECORD
