Metadata-Version: 2.1
Name: thctools
Version: 1.0.3
Summary: Used as an indicator to study the trend of the stock market. 
Home-page: https://github.com/zero-python/thctools
Author: zero
Author-email: 13256937698@163.com
License: MIT
Platform: UNKNOWN
Classifier: License :: OSI Approved :: MIT License
Classifier: Programming Language :: Python
Classifier: Programming Language :: Python :: 3
Classifier: Programming Language :: Python :: 3.5
Classifier: Programming Language :: Python :: 3.5
Classifier: Programming Language :: Python :: 3.6
Classifier: Programming Language :: Python :: 3.7
Classifier: Intended Audience :: Developers
Classifier: Operating System :: OS Independent
